data_warehouse/__init__.py
data_warehouse-1.0.0.dist-info/LICENSE
data_warehouse-1.0.0.dist-info/METADATA
data_warehouse-1.0.0.dist-info/WHEEL
data_warehouse-1.0.0.dist-info/top_level.txt
data_warehouse-1.0.0.dist-info/RECORD
